CHANGES.txt
MANIFEST.in
README.txt
setup.cfg
setup.py
quantumcore/__init__.py
quantumcore.exceptions.egg-info/PKG-INFO
quantumcore.exceptions.egg-info/SOURCES.txt
quantumcore.exceptions.egg-info/dependency_links.txt
quantumcore.exceptions.egg-info/entry_points.txt
quantumcore.exceptions.egg-info/namespace_packages.txt
quantumcore.exceptions.egg-info/not-zip-safe
quantumcore.exceptions.egg-info/requires.txt
quantumcore.exceptions.egg-info/top_level.txt
quantumcore/exceptions/__init__.py