Metadata-Version: 1.0
Name: quantumcore.exceptions
Version: 0.1.1dev
Summary: Common exceptions for thw QuantumCore libraries.
Home-page: http://quantumcore.org
Author: Christian Scholz
Author-email: cs@comlounge.net
License: BSD
Keywords: exceptions quantumcore library cms
Platform: UNKNOWN
Classifier: Programming Language :: Python
Classifier: Topic :: Software Development :: Libraries :: Python Modules
